Metadata-Version: 2.1
Name: percache
Version: 0.4.4
Summary: Persistently cache results of callables
Home-page: https://hg.sr.ht/~obensonne/percache
Author: Oben Sonne
Author-email: obensonne@googlemail.com
License: MIT License
Platform: UNKNOWN
Classifier: Development Status :: 5 - Production/Stable
Classifier: License :: OSI Approved :: MIT License
Classifier: Operating System :: OS Independent
Classifier: Programming Language :: Python
Classifier: Programming Language :: Python :: 3
Classifier: Topic :: Software Development
Classifier: Intended Audience :: Developers
